logic.py
bsb_backend_pack-3.0.data/scripts/current-value-holdings.py
bsb_backend_pack-3.0.data/scripts/driver.py
bsb_backend_pack-3.0.data/scripts/seven_day_data.py
bsb_backend_pack-3.0.data/scripts/testScript.py
bsb_backend_pack-3.0.dist-info/METADATA
bsb_backend_pack-3.0.dist-info/WHEEL
bsb_backend_pack-3.0.dist-info/namespace_packages.txt
bsb_backend_pack-3.0.dist-info/top_level.txt
bsb_backend_pack-3.0.dist-info/zip-safe
bsb_backend_pack-3.0.dist-info/RECORD
