Metadata-Version: 2.1
Name: bsb-backend-pack
Version: 3.0
Summary: UNKNOWN
Home-page: UNKNOWN
Author: 
Author-email: 
Maintainer: 
Maintainer-email: 
License: UNKNOWN
Platform: UNKNOWN
Classifier: Development Status :: 3 - Alpha
Classifier: Programming Language :: Python
Requires-Dist: alpaca-trade-api
Requires-Dist: datetime
Requires-Dist: numpy
Requires-Dist: pandas
Requires-Dist: yfinance
